CHANGES.txt
LICENSE.txt
MANIFEST.in
README.rst
setup.cfg
setup.py
cmdparser/__init__.py
cmdparser/cmdparser.py
cmdparser/datetimeparse.py
cmdparser.egg-info/PKG-INFO
cmdparser.egg-info/SOURCES.txt
cmdparser.egg-info/dependency_links.txt
cmdparser.egg-info/top_level.txt
test/test_cmdparser.py
test/test_datetimeparse.py