Metadata-Version: 1.1
Name: cmdparser
Version: 1.0.1
Summary: Command parsing extensions to the cmd module.
Home-page: http://cartroo.github.com/ttrack/cmdparser.html
Author: Andy Pearce
Author-email: andy@andy-pearce.com
License: LICENSE.txt
Platform: UNKNOWN
Classifier: Development Status :: 5 - Production/Stable
Classifier: Intended Audience :: Developers
Classifier: License :: OSI Approved :: MIT License
Classifier: Natural Language :: English
Classifier: Operating System :: OS Independent
Classifier: Programming Language :: Python
Classifier: Programming Language :: Python :: 2
Classifier: Topic :: Software Development :: Libraries
Classifier: Topic :: Software Development :: Libraries :: Python Modules
Classifier: Topic :: Text Processing
Classifier: Topic :: Text Processing :: General
